injx/__init__.py
injx/analyzer.py
injx/cleanup_strategy.py
injx/container.py
injx/contextual.py
injx/dependencies.py
injx/exceptions.py
injx/injection.py
injx/logging.py
injx/metaclasses.py
injx/provider_spec.py
injx/py.typed
injx/registry.py
injx/scope_context.py
injx/scope_data.py
injx/tokens.py
injx/types.py
injx/protocols/__init__.py
injx/protocols/cleanup.py
injx/protocols/container.py
injx/protocols/resolvable.py
injx/protocols/resources.py
injx-0.2.0.dist-info/METADATA
injx-0.2.0.dist-info/WHEEL
injx-0.2.0.dist-info/licenses/LICENSE
injx-0.2.0.dist-info/licenses/NOTICE
injx-0.2.0.dist-info/RECORD
