Metadata-Version: 2.4
Name: injx
Version: 0.2.0
Summary: Type-safe dependency injection for Python 3.13+
Project-URL: Homepage, https://github.com/qriusglobal/injx
Project-URL: Repository, https://github.com/qriusglobal/injx
Project-URL: Documentation, https://github.com/qriusglobal/injx#readme
Project-URL: Bug Tracker, https://github.com/qriusglobal/injx/issues
Project-URL: Changelog, https://github.com/qriusglobal/injx/releases
Project-URL: CI, https://github.com/qriusglobal/injx/actions
Author-email: Qrius Global <mishal@qrius.global>
License: Apache-2.0
License-File: LICENSE
License-File: NOTICE
Keywords: async,dependency-injection,di,ioc,python3.13,type-safe
Classifier: Development Status :: 3 - Alpha
Classifier: Framework :: AsyncIO
Classifier: Intended Audience :: Developers
Classifier: License :: OSI Approved :: Apache Software License
Classifier: Operating System :: OS Independent
Classifier: Programming Language :: Python :: 3 :: Only
Classifier: Programming Language :: Python :: 3.13
Classifier: Topic :: Software Development :: Libraries
Classifier: Typing :: Typed
Requires-Python: >=3.13
Provides-Extra: dev
Requires-Dist: actionlint-py>=1.7.7; extra == 'dev'
Requires-Dist: aiosqlite>=0.19; extra == 'dev'
Requires-Dist: asyncpg>=0.29; extra == 'dev'
Requires-Dist: basedpyright>=1.23.0; extra == 'dev'
Requires-Dist: commitizen>=3.30; extra == 'dev'
Requires-Dist: httpx>=0.27; extra == 'dev'
Requires-Dist: playwright>=1.44; extra == 'dev'
Requires-Dist: pre-commit>=3.7; extra == 'dev'
Requires-Dist: pytest-asyncio>=0.23; extra == 'dev'
Requires-Dist: pytest-cov>=5.0.0; extra == 'dev'
Requires-Dist: pytest-xdist>=3.5.0; extra == 'dev'
Requires-Dist: pytest>=8.2; extra == 'dev'
Requires-Dist: python-semantic-release>=9.0; extra == 'dev'
Requires-Dist: ruff>=0.8.0; extra == 'dev'
Requires-Dist: sqlalchemy>=2.0; extra == 'dev'
Provides-Extra: docs
Requires-Dist: beautifulsoup4>=4.13; extra == 'docs'
Requires-Dist: html2text>=2025.1; extra == 'docs'
Requires-Dist: mike>=2.0; extra == 'docs'
Requires-Dist: mkdocs-llmstxt>=0.3; extra == 'docs'
Requires-Dist: mkdocs-material>=9.6; extra == 'docs'
Requires-Dist: mkdocs-minify-plugin>=0.8; extra == 'docs'
Requires-Dist: mkdocs>=1.6; extra == 'docs'
Requires-Dist: mkdocstrings[python]>=0.30; extra == 'docs'
Provides-Extra: test
Requires-Dist: pytest-asyncio>=0.23; extra == 'test'
Requires-Dist: pytest-cov>=5.0.0; extra == 'test'
Requires-Dist: pytest-xdist>=3.5.0; extra == 'test'
Requires-Dist: pytest>=8.2; extra == 'test'
